[
  {
    "nickname": "",
    "anniversary": "",
    "title": "",
    "telephone_fax": "",
    "homepage": "",
    "secondary_address": "",
    "mobilephone": "",
    "py/object": "model.contact.Contact",
    "email": "",
    "birthday_year": "",
    "all_emails_from_homepage": null,
    "workphone": "",
    "company": "",
    "company_address": "",
    "email2": "",
    "homephone": "",
    "lastname": "",
    "firstname": "",
    "secondaryphone": "",
    "middlename": "",
    "email3": "",
    "all_phones_from_homepage": null,
    "ident": null,
    "secondary_notes": ""
  },
  {
    "nickname": "nicknameWT3joN",
    "anniversary": "anniversaryoDOOu",
    "title": "titleSaxJs7iaB",
    "telephone_fax": "telephone_faxJFo",
    "homepage": "homepageu",
    "secondary_address": "secondary_addressGoQgVzo8B",
    "mobilephone": "mobilephoneM",
    "py/object": "model.contact.Contact",
    "email": "emailp7Sti0fT",
    "birthday_year": "birthday_yearm5Q",
    "all_emails_from_homepage": null,
    "workphone": "workphoneo1Byq",
    "company": "company15af9",
    "company_address": "company_addressgC68EuJ",
    "email2": "email2boFy",
    "homephone": "homephonegLXVvcFmQ",
    "lastname": "lastname5",
    "firstname": "firstnameu",
    "secondaryphone": "secondaryphone6Y3nA",
    "middlename": "middlenamehON",
    "email3": "email3PV3H4ssL",
    "all_phones_from_homepage": null,
    "ident": null,
    "secondary_notes": "secondary_notes7d9K9"
  },
  {
    "nickname": "nicknameG",
    "anniversary": "anniversaryf",
    "title": "title0b",
    "telephone_fax": "telephone_faxAS",
    "homepage": "homepageE",
    "secondary_address": "secondary_addressmhxX",
    "mobilephone": "mobilephonet2XVMAc",
    "py/object": "model.contact.Contact",
    "email": "emaildC",
    "birthday_year": "birthday_yearpZMg3L",
    "all_emails_from_homepage": null,
    "workphone": "workphone1hTDS8",
    "company": "company73Ncr5",
    "company_address": "company_address4t9HS2",
    "email2": "email2DVw4p",
    "homephone": "homephoneXyWe",
    "lastname": "lastname5fe5a",
    "firstname": "firstnamek",
    "secondaryphone": "secondaryphoneN4XY",
    "middlename": "middlenameMnes",
    "email3": "email3Enme",
    "all_phones_from_homepage": null,
    "ident": null,
    "secondary_notes": "secondary_notesXVfn"
  },
  {
    "nickname": "nicknamesrKJbTQ6q",
    "anniversary": "anniversarycwK",
    "title": "titleby",
    "telephone_fax": "telephone_fax5DjgHN",
    "homepage": "homepageUUVZfN",
    "secondary_address": "secondary_addresswz",
    "mobilephone": "mobilephone088eqe5r",
    "py/object": "model.contact.Contact",
    "email": "emailbzab",
    "birthday_year": "birthday_yearJx",
    "all_emails_from_homepage": null,
    "workphone": "workphonemaHjt0K",
    "company": "companymv",
    "company_address": "company_addressfSJN3",
    "email2": "email2PBBV4",
    "homephone": "homephoneTDPd",
    "lastname": "lastname2BYG9t",
    "firstname": "firstnameFB2Bp",
    "secondaryphone": "secondaryphoneNm5gKQ",
    "middlename": "middlename",
    "email3": "email3yn",
    "all_phones_from_homepage": null,
    "ident": null,
    "secondary_notes": "secondary_notesAtYsy0fYH"
  },
  {
    "nickname": "nicknameqhu",
    "anniversary": "anniversaryUM",
    "title": "titlel",
    "telephone_fax": "telephone_fax5QWLJs",
    "homepage": "homepage",
    "secondary_address": "secondary_addressQTQRJBop",
    "mobilephone": "mobilephone",
    "py/object": "model.contact.Contact",
    "email": "email3A2RfWEdn",
    "birthday_year": "birthday_yearq",
    "all_emails_from_homepage": null,
    "workphone": "workphoneCndukQo6",
    "company": "company",
    "company_address": "company_addressaT7Qqa",
    "email2": "email2s9SSU",
    "homephone": "homephone1",
    "lastname": "lastnames0ukbTxg",
    "firstname": "firstnames4UK7iGs",
    "secondaryphone": "secondaryphoneS",
    "middlename": "middlename7CgAnSD",
    "email3": "email3x",
    "all_phones_from_homepage": null,
    "ident": null,
    "secondary_notes": "secondary_notesTJad"
  },
  {
    "nickname": "nicknameAhi",
    "anniversary": "anniversaryHWr",
    "title": "titletZ4",
    "telephone_fax": "telephone_faxzfvJXzTz",
    "homepage": "homepageQW7yxL",
    "secondary_address": "secondary_addresstr",
    "mobilephone": "mobilephoneh11iPcnTq",
    "py/object": "model.contact.Contact",
    "email": "email",
    "birthday_year": "birthday_year0I",
    "all_emails_from_homepage": null,
    "workphone": "workphone",
    "company": "companyRXsO0Ru",
    "company_address": "company_addressGQ2OXRirb",
    "email2": "email2XYRGK",
    "homephone": "homephonemDOnMb",
    "lastname": "lastnamejqrhEb",
    "firstname": "firstnameP97o5",
    "secondaryphone": "secondaryphone5",
    "middlename": "middlenameBmE",
    "email3": "email30G3rHYK",
    "all_phones_from_homepage": null,
    "ident": null,
    "secondary_notes": "secondary_notes6f"
  }
]